lassen/__init__.py
lassen/alembic/__init__.py
lassen/alembic/cli.py
lassen/alembic/io.py
lassen/alembic/runner.py
lassen/assets/__init__.py
lassen/assets/alembic.ini
lassen/assets/script.py.mako
lassen/aws.py
lassen/constants.py
lassen/core/__init__.py
lassen/core/config.py
lassen/datasets/__init__.py
lassen/datasets/dataset_helpers.py
lassen/datasets/pyarrow_schemas.py
lassen/db/__init__.py
lassen/db/base_class.py
lassen/db/columns.py
lassen/db/session.py
lassen/enums.py
lassen/io.py
lassen/py.typed
lassen/queries.py
lassen/schema.py
lassen/shared.py
lassen/store/__init__.py
lassen/store/base.py
lassen/store/filter.py
lassen/store/s3.py
lassen/stubs/__init__.py
lassen/stubs/base.py
lassen/stubs/common/__init__.py
lassen/stubs/common/filters.py
lassen/stubs/common/str_formatters.py
lassen/stubs/common/stub_imports.py
lassen/stubs/common/typehints.py
lassen/stubs/definition.py
lassen/stubs/field.py
lassen/stubs/generate.py
lassen/stubs/generators/__init__.py
lassen/stubs/generators/schema.py
lassen/stubs/generators/store.py
lassen/stubs/templates/__init__.py
lassen/stubs/templates/schema.py.j2
lassen/stubs/templates/sqlalchemy.py.j2
lassen/tests/__init__.py
lassen/tests/conftest.py
lassen/tests/conftest_helpers/__init__.py
lassen/tests/conftest_helpers/aws.py
lassen/tests/datasets/__init__.py
lassen/tests/datasets/test_dataset_helpers.py
lassen/tests/datasets/test_pyarrow_schemas.py
lassen/tests/db/__init__.py
lassen/tests/db/test_session.py
lassen/tests/fixtures/__init__.py
lassen/tests/fixtures/stubs/expected_schema.py
lassen/tests/fixtures/stubs/expected_schema_public.py
lassen/tests/fixtures/stubs/expected_store.py
lassen/tests/fixtures/stubs/fixtures.py
lassen/tests/fixtures/test_harness/README.md
lassen/tests/fixtures/test_harness/pyproject.toml
lassen/tests/fixtures/test_harness/test_harness/__init__.py
lassen/tests/fixtures/test_harness/test_harness/migrations/62bf8def9fb1_new_migration.py
lassen-0.5.2.dist-info/LICENSE
lassen-0.5.2.dist-info/METADATA
lassen-0.5.2.dist-info/WHEEL
lassen-0.5.2.dist-info/entry_points.txt
lassen-0.5.2.dist-info/RECORD
