Metadata-Version: 2.1
Name: lassen
Version: 0.5.2
Summary: Common webapp scaffolding.
Author: Pierce Freeman
Author-email: pierce@freeman.vc
Requires-Python: >=3.11,<4.0
Classifier: Programming Language :: Python :: 3
Classifier: Programming Language :: Python :: 3.11
Classifier: Programming Language :: Python :: 3.12
Provides-Extra: aws
Provides-Extra: database
Provides-Extra: datasets
Requires-Dist: Jinja2 (>=3.1.2,<4.0.0)
Requires-Dist: SQLAlchemy (>=2.0.15,<3.0.0) ; extra == "database"
Requires-Dist: aioboto3 (>=12.0.0,<13.0.0) ; extra == "aws"
Requires-Dist: alembic (>=1.11.1,<2.0.0)
Requires-Dist: alembic-autogenerate-enums (>=0.1.1,<0.2.0)
Requires-Dist: brotli (>=1.0.9,<2.0.0) ; extra == "aws"
Requires-Dist: click (>=8.1.3,<9.0.0)
Requires-Dist: datasets (>=2.13.0,<3.0.0) ; extra == "datasets"
Requires-Dist: fastapi (>=0.101.0,<0.102.0)
Requires-Dist: inflection (>=0.5.1,<0.6.0)
Requires-Dist: numpy (>=1.24.3,<2.0.0) ; extra == "datasets"
Requires-Dist: pandas (>=2.0.2,<3.0.0) ; extra == "datasets"
Requires-Dist: psycopg2 (>=2.9.6,<3.0.0) ; extra == "database"
Requires-Dist: pydantic (>=2.2.1,<3.0.0)
Requires-Dist: pydantic-settings (>=2.0.3,<3.0.0)
Requires-Dist: python-dotenv (>=1.0.0,<2.0.0)
